LICENSE.txt
MANIFEST.in
README.txt
setup.py
examples/__init__.py
examples/withDummy/__init__.py
examples/withDummy/_logo_xrQt.py
examples/withDummy/_logo_xrt_rotated.py
examples/withDummy/_logo_xrwt.py
examples/withDummy/logo-python.png
examples/withDummy/logo_xrt.py
examples/withDummy/xrt_demo.py
examples/withRaycing/__init__.py
examples/withRaycing/00_xRayCalculator/__init__.py
examples/withRaycing/00_xRayCalculator/_calc_Balder_power.py
examples/withRaycing/00_xRayCalculator/_calc_absorption_Ar.py
examples/withRaycing/00_xRayCalculator/_calc_coated_mirror_RhPt.py
examples/withRaycing/00_xRayCalculator/_calc_crystal_333_511.py
examples/withRaycing/00_xRayCalculator/_calc_crystal_440.py
examples/withRaycing/00_xRayCalculator/_calc_crystal_Shvydko.py
examples/withRaycing/00_xRayCalculator/_calc_crystal_Si444.py
examples/withRaycing/00_xRayCalculator/_calc_crystal_forward.py
examples/withRaycing/00_xRayCalculator/_calc_crystal_rocking_curve_311.py
examples/withRaycing/00_xRayCalculator/_calc_crystal_rocking_curve_energy.py
examples/withRaycing/00_xRayCalculator/_calc_crystal_rocking_curve_square.py
examples/withRaycing/00_xRayCalculator/_calc_crystal_shifted.py
examples/withRaycing/00_xRayCalculator/_calc_mirror_Balder.py
examples/withRaycing/00_xRayCalculator/_calc_mirror_Rh.py
examples/withRaycing/00_xRayCalculator/_calc_mirror_phase.py
examples/withRaycing/00_xRayCalculator/_calc_mirror_soft.py
examples/withRaycing/00_xRayCalculator/_calc_multilayer_E_B4C.py
examples/withRaycing/00_xRayCalculator/_calc_multilayer_error.py
examples/withRaycing/00_xRayCalculator/_calc_transmittivityAl.py
examples/withRaycing/00_xRayCalculator/_calc_transmittivitySi.py
examples/withRaycing/00_xRayCalculator/_calc_undulator.py
examples/withRaycing/00_xRayCalculator/_calc_undulator_tune_spectra.py
examples/withRaycing/00_xRayCalculator/calc_absorption.py
examples/withRaycing/00_xRayCalculator/calc_bm.py
examples/withRaycing/00_xRayCalculator/calc_carbon_contamination.py
xrt.egg-info/PKG-INFO
xrt.egg-info/SOURCES.txt
xrt.egg-info/dependency_links.txt
xrt.egg-info/not-zip-safe
xrt.egg-info/requires.txt
xrt.egg-info/top_level.txt
