Metadata-Version: 2.1
Name: xrt
Version: 1.6.1
Summary: Ray tracing and wave propagation in x-ray regime, primarily meant for modeling synchrotron sources, beamlines and beamline elements. Includes a GUI for creating a beamline and viewing it in 3D.
Home-page: http://xrt.readthedocs.io
Author: Konstantin Klementiev, Roman Chernikov
Author-email: konstantin.klementiev@gmail.com, rchernikov@gmail.com
License: MIT License
Platform: OS Independent
Classifier: Development Status :: 5 - Production/Stable
Classifier: Intended Audience :: Science/Research
Classifier: Natural Language :: English
Classifier: Operating System :: OS Independent
Classifier: Programming Language :: Python :: 2
Classifier: Programming Language :: Python :: 3
Classifier: License :: OSI Approved :: MIT License
Classifier: Topic :: Scientific/Engineering :: Physics
Classifier: Topic :: Scientific/Engineering :: Visualization
License-File: LICENSE.txt
Requires-Dist: numpy>=1.8.0
Requires-Dist: scipy>=0.17.0
Requires-Dist: matplotlib>=2.0.0
Requires-Dist: sphinx>=1.6.2
Requires-Dist: sphinxcontrib-jquery
Requires-Dist: distro
Requires-Dist: colorama
Requires-Dist: pyopencl
Requires-Dist: pyopengl
Requires-Dist: siphash24
Provides-Extra: pyqt5
Requires-Dist: pyqt5; extra == "pyqt5"
Requires-Dist: PyQtWebEngine; extra == "pyqt5"
